{"nodes": [{"id": "test_models_test_currency_creation", "label": "test_currency_creation", "file_type": "code", "source_file": "tests/test_models.py", "source_location": "tests/test_models.py:14", "source_url": null, "captured_at": null, "author": null, "contributor": null}, {"id": "test_models_test_ticker_creation", "label": "test_ticker_creation", "file_type": "code", "source_file": "tests/test_models.py", "source_location": "tests/test_models.py:19", "source_url": null, "captured_at": null, "author": null, "contributor": null}, {"id": "test_models_test_wallet_creation", "label": "test_wallet_creation", "file_type": "code", "source_file": "tests/test_models.py", "source_location": "tests/test_models.py:28", "source_url": null, "captured_at": null, "author": null, "contributor": null}, {"id": "test_models_test_portfolio_creation", "label": "test_portfolio_creation", "file_type": "code", "source_file": "tests/test_models.py", "source_location": "tests/test_models.py:39", "source_url": null, "captured_at": null, "author": null, "contributor": null}, {"id": "test_models_test_transaction_creation", "label": "test_transaction_creation", "file_type": "code", "source_file": "tests/test_models.py", "source_location": "tests/test_models.py:51", "source_url": null, "captured_at": null, "author": null, "contributor": null}, {"id": "test_models_test_backtest_config_creation", "label": "test_backtest_config_creation", "file_type": "code", "source_file": "tests/test_models.py", "source_location": "tests/test_models.py:66", "source_url": null, "captured_at": null, "author": null, "contributor": null}], "edges": [{"source": "test_models_test_currency_creation", "target": "models_currency", "relation": "references", "confidence": "EXTRACTED", "confidence_score": 1.0, "source_file": "tests/test_models.py", "source_location": "tests/test_models.py:14", "weight": 1.0}, {"source": "test_models_test_ticker_creation", "target": "models_ticker", "relation": "references", "confidence": "EXTRACTED", "confidence_score": 1.0, "source_file": "tests/test_models.py", "source_location": "tests/test_models.py:19", "weight": 1.0}, {"source": "test_models_test_wallet_creation", "target": "models_wallet", "relation": "references", "confidence": "EXTRACTED", "confidence_score": 1.0, "source_file": "tests/test_models.py", "source_location": "tests/test_models.py:28", "weight": 1.0}, {"source": "test_models_test_portfolio_creation", "target": "models_portfolio", "relation": "references", "confidence": "EXTRACTED", "confidence_score": 1.0, "source_file": "tests/test_models.py", "source_location": "tests/test_models.py:39", "weight": 1.0}, {"source": "test_models_test_transaction_creation", "target": "models_transaction", "relation": "references", "confidence": "EXTRACTED", "confidence_score": 1.0, "source_file": "tests/test_models.py", "source_location": "tests/test_models.py:51", "weight": 1.0}, {"source": "test_models_test_backtest_config_creation", "target": "models_backtestconfig", "relation": "references", "confidence": "EXTRACTED", "confidence_score": 1.0, "source_file": "tests/test_models.py", "source_location": "tests/test_models.py:66", "weight": 1.0}], "hyperedges": []}